pytest_schedule/__init__.py
pytest_schedule/__main__.py
pytest_schedule/generate.py
pytest_schedule/py_schedule.py
pytest_schedule-0.0.8.dist-info/METADATA
pytest_schedule-0.0.8.dist-info/WHEEL
pytest_schedule-0.0.8.dist-info/entry_points.txt
pytest_schedule-0.0.8.dist-info/top_level.txt
pytest_schedule-0.0.8.dist-info/RECORD
