Metadata-Version: 2.1
Name: pytest-schedule
Version: 0.0.8
Summary: Automate and customize test scheduling effortlessly on local machines.
Author-email: Oleg Matskiv <alpaca00tuha@gmail.com>
License: MIT
Keywords: pytest,schedule,automation,parallel,concurrent,tests,test
Requires-Python: >=3.8
Requires-Dist: setuptools>=65.5.1
Requires-Dist: dpath==2.1.3
Requires-Dist: loguru==0.6.0
